{"nodes":[{"nodeID":"1215819","text":"we do or do not know who Donna Goddard's company is","type":"I","timestamp":"2023-08-31 19:27:08"},{"nodeID":"1215824","text":"Building Bright Futures","type":"I","timestamp":"2023-08-31 19:27:09"},{"nodeID":"1215829","text":"Donna Goddard's company being Building Bright Futures has never been mentioned","type":"I","timestamp":"2023-08-31 19:27:09"},{"nodeID":"1215839","text":"Donna Goddard wouldn't have left a note","type":"I","timestamp":"2023-08-31 19:27:10"},{"nodeID":"1215844","text":"Donna Goddard wouldn't have left a note to meet Nick Webster in the future","type":"I","timestamp":"2023-08-31 19:27:11"},{"nodeID":"1215849","text":"Donna Goddard knew they were going to kill Nick Webster","type":"I","timestamp":"2023-08-31 19:27:11"},{"nodeID":"1215854","text":"Female 3's idea about Donna Goddard being involved isn't working anymore","type":"I","timestamp":"2023-08-31 19:27:12"},{"nodeID":"1215859","text":"Female 1 was just trying to find a link between Donna Goddard's real estate company, and the one buying this","type":"I","timestamp":"2023-08-31 19:27:12"},{"nodeID":"1215864","text":"Female 1 can't figure out a link to Donna's real estate company","type":"I","timestamp":"2023-08-31 19:27:13"},{"nodeID":"1215874","text":"there was no incentive for Donna Goddard to kill someone","type":"I","timestamp":"2023-08-31 19:27:14"},{"nodeID":"1215879","text":"Donna Goddard was talking to the husband, not the wife","type":"I","timestamp":"2023-08-31 19:27:14"},{"nodeID":"1215889","text":"Donna Goddard does say something odd","type":"I","timestamp":"2023-08-31 19:27:15"},{"nodeID":"1215894","text":"Donna Goddard is crying a lot","type":"I","timestamp":"2023-08-31 19:27:15"},{"nodeID":"1215899","text":"if only Donna Goddard had been faster, maybe she could have made a difference","type":"I","timestamp":"2023-08-31 19:27:16"},{"nodeID":"1215908","text":"Donna Goddard was helping Nick Webster","type":"I","timestamp":"2023-08-31 19:27:17"},{"nodeID":"1474446","text":"Female 2: Do we know who's her company","type":"L","timestamp":"2024-03-02 17:06:01"},{"nodeID":"1474447","text":"Analysing","type":"YA","timestamp":"2024-03-02 17:06:01","scheme":"Analysing","schemeID":"75"},{"nodeID":"1474448","text":"Lara: Female 2: Do we know who's her company","type":"L","timestamp":"2024-03-02 17:06:01"},{"nodeID":"1474449","text":"Pure Questioning","type":"YA","timestamp":"2024-03-02 17:06:01","scheme":"PureQuestioning","schemeID":"91"},{"nodeID":"1474450","text":"Female 2: Building Bright Futures","type":"L","timestamp":"2024-03-02 17:06:02"},{"nodeID":"1474451","text":"Analysing","type":"YA","timestamp":"2024-03-02 17:06:02","scheme":"Analysing","schemeID":"75"},{"nodeID":"1474452","text":"Lara: Female 2: Building Bright Futures","type":"L","timestamp":"2024-03-02 17:06:02"},{"nodeID":"1474453","text":"Asserting","type":"YA","timestamp":"2024-03-02 17:06:02","scheme":"Asserting","schemeID":"74"},{"nodeID":"1474454","text":"Female 2: that's never been mentioned has it","type":"L","timestamp":"2024-03-02 17:06:02"},{"nodeID":"1474455","text":"Analysing","type":"YA","timestamp":"2024-03-02 17:06:02","scheme":"Analysing","schemeID":"75"},{"nodeID":"1474456","text":"Lara: Female 2: that's never been mentioned has it","type":"L","timestamp":"2024-03-02 17:06:02"},{"nodeID":"1474457","text":"Assertive Questioning","type":"YA","timestamp":"2024-03-02 17:06:02","scheme":"AssertiveQuestioning","schemeID":"73"},{"nodeID":"1474458","text":"Building Bright Futures was mentioned in the article","type":"I","timestamp":"2024-03-02 17:06:03"},{"nodeID":"1474459","text":"Female 3: Maybe in the article","type":"L","timestamp":"2024-03-02 17:06:03"},{"nodeID":"1474460","text":"Analysing","type":"YA","timestamp":"2024-03-02 17:06:03","scheme":"Analysing","schemeID":"75"},{"nodeID":"1474461","text":"Lara: Female 3: Maybe in the article","type":"L","timestamp":"2024-03-02 17:06:03"},{"nodeID":"1474462","text":"Hypothesising","type":"YA","timestamp":"2024-03-02 17:06:03","scheme":"Hypothesising","schemeID":"410"},{"nodeID":"1474463","text":"Female 3:  she wouldn't have left a note","type":"L","timestamp":"2024-03-02 17:06:04"},{"nodeID":"1474464","text":"Analysing","type":"YA","timestamp":"2024-03-02 17:06:04","scheme":"Analysing","schemeID":"75"},{"nodeID":"1474465","text":"Lara: Female 3:  she wouldn't have left a note","type":"L","timestamp":"2024-03-02 17:06:04"},{"nodeID":"1474466","text":"Asserting","type":"YA","timestamp":"2024-03-02 17:06:04","scheme":"Asserting","schemeID":"74"},{"nodeID":"1474467","text":"Female 3: she wouldn't have left a note to meet him in the future, right","type":"L","timestamp":"2024-03-02 17:06:04"},{"nodeID":"1474468","text":"Analysing","type":"YA","timestamp":"2024-03-02 17:06:04","scheme":"Analysing","schemeID":"75"},{"nodeID":"1474469","text":"Lara: Female 3: she wouldn't have left a note to meet him in the future, right","type":"L","timestamp":"2024-03-02 17:06:04"},{"nodeID":"1474470","text":"Assertive Questioning","type":"YA","timestamp":"2024-03-02 17:06:04","scheme":"AssertiveQuestioning","schemeID":"73"},{"nodeID":"1474471","text":"Female 3: she knew they were going to kill him","type":"L","timestamp":"2024-03-02 17:06:05"},{"nodeID":"1474472","text":"Analysing","type":"YA","timestamp":"2024-03-02 17:06:05","scheme":"Analysing","schemeID":"75"},{"nodeID":"1474473","text":"Lara: Female 3: she knew they were going to kill him","type":"L","timestamp":"2024-03-02 17:06:05"},{"nodeID":"1474474","text":"Asserting","type":"YA","timestamp":"2024-03-02 17:06:05","scheme":"Asserting","schemeID":"74"},{"nodeID":"1474475","text":"Female 3: my idea isn't working anymore","type":"L","timestamp":"2024-03-02 17:06:06"},{"nodeID":"1474476","text":"Analysing","type":"YA","timestamp":"2024-03-02 17:06:06","scheme":"Analysing","schemeID":"75"},{"nodeID":"1474477","text":"Lara: Female 3: my idea isn't working anymore","type":"L","timestamp":"2024-03-02 17:06:06"},{"nodeID":"1474478","text":"Asserting","type":"YA","timestamp":"2024-03-02 17:06:06","scheme":"Asserting","schemeID":"74"},{"nodeID":"1474479","text":"Female 1:  I was just trying to find a link between her real estate company, and the one buying this","type":"L","timestamp":"2024-03-02 17:06:06"},{"nodeID":"1474480","text":"Analysing","type":"YA","timestamp":"2024-03-02 17:06:06","scheme":"Analysing","schemeID":"75"},{"nodeID":"1474481","text":"Lara: Female 1:  I was just trying to find a link between her real estate company, and the one buying this","type":"L","timestamp":"2024-03-02 17:06:06"},{"nodeID":"1474482","text":"Asserting","type":"YA","timestamp":"2024-03-02 17:06:06","scheme":"Asserting","schemeID":"74"},{"nodeID":"1474483","text":"Female 1: I can't figure","type":"L","timestamp":"2024-03-02 17:06:07"},{"nodeID":"1474484","text":"Analysing","type":"YA","timestamp":"2024-03-02 17:06:07","scheme":"Analysing","schemeID":"75"},{"nodeID":"1474485","text":"Lara: Female 1: I can't figure","type":"L","timestamp":"2024-03-02 17:06:07"},{"nodeID":"1474486","text":"Asserting","type":"YA","timestamp":"2024-03-02 17:06:07","scheme":"Asserting","schemeID":"74"},{"nodeID":"1474487","text":"Donna Goddard was trying to sell the land to Nick Webster","type":"I","timestamp":"2024-03-02 17:06:08"},{"nodeID":"1474488","text":"Female 2: Let's say she was trying to sell the land to him","type":"L","timestamp":"2024-03-02 17:06:08"},{"nodeID":"1474489","text":"Analysing","type":"YA","timestamp":"2024-03-02 17:06:08","scheme":"Analysing","schemeID":"75"},{"nodeID":"1474490","text":"Lara: Female 2: Let's say she was trying to sell the land to him","type":"L","timestamp":"2024-03-02 17:06:08"},{"nodeID":"1474491","text":"Hypothesising","type":"YA","timestamp":"2024-03-02 17:06:08","scheme":"Hypothesising","schemeID":"410"},{"nodeID":"1474492","text":"Female 2: there was no incentive for her to kill someone","type":"L","timestamp":"2024-03-02 17:06:08"},{"nodeID":"1474493","text":"Analysing","type":"YA","timestamp":"2024-03-02 17:06:08","scheme":"Analysing","schemeID":"75"},{"nodeID":"1474494","text":"Lara: Female 2: there was no incentive for her to kill someone","type":"L","timestamp":"2024-03-02 17:06:08"},{"nodeID":"1474495","text":"Female 2: she was talking to the husband, not the wife","type":"L","timestamp":"2024-03-02 17:06:09"},{"nodeID":"1474496","text":"Analysing","type":"YA","timestamp":"2024-03-02 17:06:09","scheme":"Analysing","schemeID":"75"},{"nodeID":"1474497","text":"Lara: Female 2: she was talking to the husband, not the wife","type":"L","timestamp":"2024-03-02 17:06:09"},{"nodeID":"1474498","text":"Asserting","type":"YA","timestamp":"2024-03-02 17:06:09","scheme":"Asserting","schemeID":"74"},{"nodeID":"1474499","text":"Donna Goddard found out through the grapevine","type":"I","timestamp":"2024-03-02 17:06:10"},{"nodeID":"1474500","text":"Female 1: It might just be that she found out through the grapevine","type":"L","timestamp":"2024-03-02 17:06:10"},{"nodeID":"1474501","text":"Analysing","type":"YA","timestamp":"2024-03-02 17:06:10","scheme":"Analysing","schemeID":"75"},{"nodeID":"1474502","text":"Lara: Female 1: It might just be that she found out through the grapevine","type":"L","timestamp":"2024-03-02 17:06:10"},{"nodeID":"1474503","text":"Hypothesising","type":"YA","timestamp":"2024-03-02 17:06:10","scheme":"Hypothesising","schemeID":"410"},{"nodeID":"1474504","text":"Female 2: she does say something odd","type":"L","timestamp":"2024-03-02 17:06:11"},{"nodeID":"1474505","text":"Analysing","type":"YA","timestamp":"2024-03-02 17:06:11","scheme":"Analysing","schemeID":"75"},{"nodeID":"1474506","text":"Lara: Female 2: she does say something odd","type":"L","timestamp":"2024-03-02 17:06:11"},{"nodeID":"1474507","text":"Asserting","type":"YA","timestamp":"2024-03-02 17:06:11","scheme":"Asserting","schemeID":"74"},{"nodeID":"1474508","text":"Female 2:  she's crying a lot","type":"L","timestamp":"2024-03-02 17:06:11"},{"nodeID":"1474509","text":"Analysing","type":"YA","timestamp":"2024-03-02 17:06:11","scheme":"Analysing","schemeID":"75"},{"nodeID":"1474510","text":"Lara: Female 2:  she's crying a lot","type":"L","timestamp":"2024-03-02 17:06:11"},{"nodeID":"1474511","text":"Asserting","type":"YA","timestamp":"2024-03-02 17:06:11","scheme":"Asserting","schemeID":"74"},{"nodeID":"1474512","text":"Female 2: if only I'd been faster, maybe I could have made a difference","type":"L","timestamp":"2024-03-02 17:06:12"},{"nodeID":"1474513","text":"Analysing","type":"YA","timestamp":"2024-03-02 17:06:12","scheme":"Analysing","schemeID":"75"},{"nodeID":"1474514","text":"Lara: Female 2: if only I'd been faster, maybe I could have made a difference","type":"L","timestamp":"2024-03-02 17:06:12"},{"nodeID":"1474515","text":"whatever they were talking about here made a difference","type":"I","timestamp":"2024-03-02 17:06:13"},{"nodeID":"1474516","text":"Female 2: maybe whatever they were talking about here, could have made a difference","type":"L","timestamp":"2024-03-02 17:06:13"},{"nodeID":"1474517","text":"Analysing","type":"YA","timestamp":"2024-03-02 17:06:13","scheme":"Analysing","schemeID":"75"},{"nodeID":"1474518","text":"Lara: Female 2: maybe whatever they were talking about here, could have made a difference","type":"L","timestamp":"2024-03-02 17:06:13"},{"nodeID":"1474519","text":"Hypothesising","type":"YA","timestamp":"2024-03-02 17:06:13","scheme":"Hypothesising","schemeID":"410"},{"nodeID":"1474520","text":"Female 2: she was helping him","type":"L","timestamp":"2024-03-02 17:06:13"},{"nodeID":"1474521","text":"Analysing","type":"YA","timestamp":"2024-03-02 17:06:13","scheme":"Analysing","schemeID":"75"},{"nodeID":"1474522","text":"Lara: Female 2: she was helping him","type":"L","timestamp":"2024-03-02 17:06:13"},{"nodeID":"1474523","text":"Asserting","type":"YA","timestamp":"2024-03-02 17:06:13","scheme":"Asserting","schemeID":"74"},{"nodeID":"1474524","text":"Default Transition","type":"TA","timestamp":"2024-03-02 17:06:13","scheme":"Default Transition","schemeID":"82"},{"nodeID":"1474525","text":"Default Rephrase","type":"MA","timestamp":"2024-03-02 17:06:13","scheme":"Default Rephrase","schemeID":"144"},{"nodeID":"1474526","text":"Default Illocuting","type":"YA","timestamp":"2024-03-02 17:06:13","scheme":"Default Illocuting","schemeID":"168"},{"nodeID":"1474527","text":"Default Transition","type":"TA","timestamp":"2024-03-02 17:06:13","scheme":"Default Transition","schemeID":"82"},{"nodeID":"1474528","text":"Default Transition","type":"TA","timestamp":"2024-03-02 17:06:13","scheme":"Default Transition","schemeID":"82"},{"nodeID":"1474529","text":"Default Rephrase","type":"MA","timestamp":"2024-03-02 17:06:13","scheme":"Default Rephrase","schemeID":"144"},{"nodeID":"1474530","text":"Default Illocuting","type":"YA","timestamp":"2024-03-02 17:06:13","scheme":"Default Illocuting","schemeID":"168"},{"nodeID":"1474531","text":"Default Transition","type":"TA","timestamp":"2024-03-02 17:06:13","scheme":"Default Transition","schemeID":"82"},{"nodeID":"1474532","text":"Default Rephrase","type":"MA","timestamp":"2024-03-02 17:06:13","scheme":"Default Rephrase","schemeID":"144"},{"nodeID":"1474533","text":"Restating","type":"YA","timestamp":"2024-03-02 17:06:13","scheme":"Restating","schemeID":"101"},{"nodeID":"1474534","text":"Default Transition","type":"TA","timestamp":"2024-03-02 17:06:13","scheme":"Default Transition","schemeID":"82"},{"nodeID":"1474535","text":"Default Inference","type":"RA","timestamp":"2024-03-02 17:06:13","scheme":"Default Inference","schemeID":"72"},{"nodeID":"1474536","text":"Arguing","type":"YA","timestamp":"2024-03-02 17:06:13","scheme":"Arguing","schemeID":"80"},{"nodeID":"1474537","text":"Default Transition","type":"TA","timestamp":"2024-03-02 17:06:13","scheme":"Default Transition","schemeID":"82"},{"nodeID":"1474538","text":"Default Transition","type":"TA","timestamp":"2024-03-02 17:06:13","scheme":"Default Transition","schemeID":"82"},{"nodeID":"1474539","text":"Default Transition","type":"TA","timestamp":"2024-03-02 17:06:13","scheme":"Default Transition","schemeID":"82"},{"nodeID":"1474540","text":"Default Transition","type":"TA","timestamp":"2024-03-02 17:06:13","scheme":"Default Transition","schemeID":"82"},{"nodeID":"1474541","text":"Default Transition","type":"TA","timestamp":"2024-03-02 17:06:13","scheme":"Default Transition","schemeID":"82"},{"nodeID":"1474542","text":"Default Inference","type":"RA","timestamp":"2024-03-02 17:06:13","scheme":"Default Inference","schemeID":"72"},{"nodeID":"1474543","text":"Arguing","type":"YA","timestamp":"2024-03-02 17:06:13","scheme":"Arguing","schemeID":"80"},{"nodeID":"1474544","text":"Default Transition","type":"TA","timestamp":"2024-03-02 17:06:13","scheme":"Default Transition","schemeID":"82"},{"nodeID":"1474545","text":"Default Transition","type":"TA","timestamp":"2024-03-02 17:06:13","scheme":"Default Transition","schemeID":"82"},{"nodeID":"1474546","text":"Donna Goddard: if only I'd been faster, maybe I could have made a difference","type":"L","timestamp":"2024-03-02 17:06:13"},{"nodeID":"1474547","text":"Analysing","type":"YA","timestamp":"2024-03-02 17:06:13","scheme":"Analysing","schemeID":"75"},{"nodeID":"1474548","text":"Lara: Donna Goddard: if only I'd been faster, maybe I could have made a difference","type":"L","timestamp":"2024-03-02 17:06:13"},{"nodeID":"1474549","text":"Asserting","type":"YA","timestamp":"2024-03-02 17:06:13","scheme":"Asserting","schemeID":"74"},{"nodeID":"1474550","text":"Asserting","type":"YA","timestamp":"2024-03-02 17:06:13","scheme":"Asserting","schemeID":"74"},{"nodeID":"1474551","text":"Default Transition","type":"TA","timestamp":"2024-03-02 17:06:13","scheme":"Default Transition","schemeID":"82"},{"nodeID":"1474552","text":"Default Transition","type":"TA","timestamp":"2024-03-02 17:06:13","scheme":"Default Transition","schemeID":"82"},{"nodeID":"1474553","text":"Default Transition","type":"TA","timestamp":"2024-03-02 17:06:13","scheme":"Default Transition","schemeID":"82"},{"nodeID":"1474554","text":"Default Inference","type":"RA","timestamp":"2024-03-02 17:06:13","scheme":"Default Inference","schemeID":"72"},{"nodeID":"1474555","text":"Arguing","type":"YA","timestamp":"2024-03-02 17:06:13","scheme":"Arguing","schemeID":"80"},{"nodeID":"1474556","text":"Default Rephrase","type":"MA","timestamp":"2024-03-02 17:06:13","scheme":"Default Rephrase","schemeID":"144"},{"nodeID":"1474557","text":"Restating","type":"YA","timestamp":"2024-03-02 17:06:13","scheme":"Restating","schemeID":"101"},{"nodeID":"1474558","text":"Hypothesising","type":"YA","timestamp":"2024-03-02 17:06:13","scheme":"Hypothesising","schemeID":"410"}],"edges":[{"edgeID":"1918171","fromID":"1474447","toID":"1474446","formEdgeID":null},{"edgeID":"1918172","fromID":"1474448","toID":"1474447","formEdgeID":null},{"edgeID":"1918173","fromID":"1474446","toID":"1474449","formEdgeID":null},{"edgeID":"1918174","fromID":"1474449","toID":"1215819","formEdgeID":null},{"edgeID":"1918175","fromID":"1474451","toID":"1474450","formEdgeID":null},{"edgeID":"1918176","fromID":"1474452","toID":"1474451","formEdgeID":null},{"edgeID":"1918177","fromID":"1474450","toID":"1474453","formEdgeID":null},{"edgeID":"1918178","fromID":"1474453","toID":"1215824","formEdgeID":null},{"edgeID":"1918179","fromID":"1474455","toID":"1474454","formEdgeID":null},{"edgeID":"1918180","fromID":"1474456","toID":"1474455","formEdgeID":null},{"edgeID":"1918181","fromID":"1474454","toID":"1474457","formEdgeID":null},{"edgeID":"1918182","fromID":"1474457","toID":"1215829","formEdgeID":null},{"edgeID":"1918183","fromID":"1474460","toID":"1474459","formEdgeID":null},{"edgeID":"1918184","fromID":"1474461","toID":"1474460","formEdgeID":null},{"edgeID":"1918185","fromID":"1474459","toID":"1474462","formEdgeID":null},{"edgeID":"1918186","fromID":"1474462","toID":"1474458","formEdgeID":null},{"edgeID":"1918187","fromID":"1474464","toID":"1474463","formEdgeID":null},{"edgeID":"1918188","fromID":"1474465","toID":"1474464","formEdgeID":null},{"edgeID":"1918189","fromID":"1474463","toID":"1474466","formEdgeID":null},{"edgeID":"1918190","fromID":"1474466","toID":"1215839","formEdgeID":null},{"edgeID":"1918191","fromID":"1474468","toID":"1474467","formEdgeID":null},{"edgeID":"1918192","fromID":"1474469","toID":"1474468","formEdgeID":null},{"edgeID":"1918193","fromID":"1474467","toID":"1474470","formEdgeID":null},{"edgeID":"1918194","fromID":"1474470","toID":"1215844","formEdgeID":null},{"edgeID":"1918195","fromID":"1474472","toID":"1474471","formEdgeID":null},{"edgeID":"1918196","fromID":"1474473","toID":"1474472","formEdgeID":null},{"edgeID":"1918197","fromID":"1474471","toID":"1474474","formEdgeID":null},{"edgeID":"1918198","fromID":"1474474","toID":"1215849","formEdgeID":null},{"edgeID":"1918199","fromID":"1474476","toID":"1474475","formEdgeID":null},{"edgeID":"1918200","fromID":"1474477","toID":"1474476","formEdgeID":null},{"edgeID":"1918201","fromID":"1474475","toID":"1474478","formEdgeID":null},{"edgeID":"1918202","fromID":"1474478","toID":"1215854","formEdgeID":null},{"edgeID":"1918203","fromID":"1474480","toID":"1474479","formEdgeID":null},{"edgeID":"1918204","fromID":"1474481","toID":"1474480","formEdgeID":null},{"edgeID":"1918205","fromID":"1474479","toID":"1474482","formEdgeID":null},{"edgeID":"1918206","fromID":"1474482","toID":"1215859","formEdgeID":null},{"edgeID":"1918207","fromID":"1474484","toID":"1474483","formEdgeID":null},{"edgeID":"1918208","fromID":"1474485","toID":"1474484","formEdgeID":null},{"edgeID":"1918209","fromID":"1474483","toID":"1474486","formEdgeID":null},{"edgeID":"1918210","fromID":"1474486","toID":"1215864","formEdgeID":null},{"edgeID":"1918211","fromID":"1474489","toID":"1474488","formEdgeID":null},{"edgeID":"1918212","fromID":"1474490","toID":"1474489","formEdgeID":null},{"edgeID":"1918213","fromID":"1474488","toID":"1474491","formEdgeID":null},{"edgeID":"1918214","fromID":"1474491","toID":"1474487","formEdgeID":null},{"edgeID":"1918215","fromID":"1474493","toID":"1474492","formEdgeID":null},{"edgeID":"1918216","fromID":"1474494","toID":"1474493","formEdgeID":null},{"edgeID":"1918217","fromID":"1474496","toID":"1474495","formEdgeID":null},{"edgeID":"1918218","fromID":"1474497","toID":"1474496","formEdgeID":null},{"edgeID":"1918219","fromID":"1474495","toID":"1474498","formEdgeID":null},{"edgeID":"1918220","fromID":"1474498","toID":"1215879","formEdgeID":null},{"edgeID":"1918221","fromID":"1474501","toID":"1474500","formEdgeID":null},{"edgeID":"1918222","fromID":"1474502","toID":"1474501","formEdgeID":null},{"edgeID":"1918223","fromID":"1474500","toID":"1474503","formEdgeID":null},{"edgeID":"1918224","fromID":"1474503","toID":"1474499","formEdgeID":null},{"edgeID":"1918225","fromID":"1474505","toID":"1474504","formEdgeID":null},{"edgeID":"1918226","fromID":"1474506","toID":"1474505","formEdgeID":null},{"edgeID":"1918227","fromID":"1474504","toID":"1474507","formEdgeID":null},{"edgeID":"1918228","fromID":"1474507","toID":"1215889","formEdgeID":null},{"edgeID":"1918229","fromID":"1474509","toID":"1474508","formEdgeID":null},{"edgeID":"1918230","fromID":"1474510","toID":"1474509","formEdgeID":null},{"edgeID":"1918231","fromID":"1474508","toID":"1474511","formEdgeID":null},{"edgeID":"1918232","fromID":"1474511","toID":"1215894","formEdgeID":null},{"edgeID":"1918233","fromID":"1474513","toID":"1474512","formEdgeID":null},{"edgeID":"1918234","fromID":"1474514","toID":"1474513","formEdgeID":null},{"edgeID":"1918235","fromID":"1474517","toID":"1474516","formEdgeID":null},{"edgeID":"1918236","fromID":"1474518","toID":"1474517","formEdgeID":null},{"edgeID":"1918237","fromID":"1474516","toID":"1474519","formEdgeID":null},{"edgeID":"1918238","fromID":"1474519","toID":"1474515","formEdgeID":null},{"edgeID":"1918239","fromID":"1474521","toID":"1474520","formEdgeID":null},{"edgeID":"1918240","fromID":"1474522","toID":"1474521","formEdgeID":null},{"edgeID":"1918241","fromID":"1474520","toID":"1474523","formEdgeID":null},{"edgeID":"1918242","fromID":"1474523","toID":"1215908","formEdgeID":null},{"edgeID":"1918243","fromID":"1474446","toID":"1474524","formEdgeID":null},{"edgeID":"1918244","fromID":"1474524","toID":"1474450","formEdgeID":null},{"edgeID":"1918245","fromID":"1215824","toID":"1474525","formEdgeID":null},{"edgeID":"1918246","fromID":"1474525","toID":"1215819","formEdgeID":null},{"edgeID":"1918247","fromID":"1474524","toID":"1474526","formEdgeID":null},{"edgeID":"1918248","fromID":"1474526","toID":"1474525","formEdgeID":null},{"edgeID":"1918249","fromID":"1474450","toID":"1474527","formEdgeID":null},{"edgeID":"1918250","fromID":"1474527","toID":"1474454","formEdgeID":null},{"edgeID":"1918251","fromID":"1474454","toID":"1474528","formEdgeID":null},{"edgeID":"1918252","fromID":"1474528","toID":"1474459","formEdgeID":null},{"edgeID":"1918253","fromID":"1474458","toID":"1474529","formEdgeID":null},{"edgeID":"1918254","fromID":"1474529","toID":"1215829","formEdgeID":null},{"edgeID":"1918255","fromID":"1474528","toID":"1474530","formEdgeID":null},{"edgeID":"1918256","fromID":"1474530","toID":"1474529","formEdgeID":null},{"edgeID":"1918257","fromID":"1474463","toID":"1474531","formEdgeID":null},{"edgeID":"1918258","fromID":"1474531","toID":"1474467","formEdgeID":null},{"edgeID":"1918259","fromID":"1215844","toID":"1474532","formEdgeID":null},{"edgeID":"1918260","fromID":"1474532","toID":"1215839","formEdgeID":null},{"edgeID":"1918261","fromID":"1474531","toID":"1474533","formEdgeID":null},{"edgeID":"1918262","fromID":"1474533","toID":"1474532","formEdgeID":null},{"edgeID":"1918263","fromID":"1474467","toID":"1474534","formEdgeID":null},{"edgeID":"1918264","fromID":"1474534","toID":"1474471","formEdgeID":null},{"edgeID":"1918265","fromID":"1215849","toID":"1474535","formEdgeID":null},{"edgeID":"1918266","fromID":"1474535","toID":"1215844","formEdgeID":null},{"edgeID":"1918267","fromID":"1474534","toID":"1474536","formEdgeID":null},{"edgeID":"1918268","fromID":"1474536","toID":"1474535","formEdgeID":null},{"edgeID":"1918269","fromID":"1474479","toID":"1474537","formEdgeID":null},{"edgeID":"1918270","fromID":"1474537","toID":"1474483","formEdgeID":null},{"edgeID":"1918271","fromID":"1474450","toID":"1474538","formEdgeID":null},{"edgeID":"1918272","fromID":"1474538","toID":"1474479","formEdgeID":null},{"edgeID":"1918273","fromID":"1474479","toID":"1474539","formEdgeID":null},{"edgeID":"1918274","fromID":"1474539","toID":"1474488","formEdgeID":null},{"edgeID":"1918275","fromID":"1474488","toID":"1474540","formEdgeID":null},{"edgeID":"1918276","fromID":"1474540","toID":"1474492","formEdgeID":null},{"edgeID":"1918277","fromID":"1474492","toID":"1474541","formEdgeID":null},{"edgeID":"1918278","fromID":"1474541","toID":"1474495","formEdgeID":null},{"edgeID":"1918279","fromID":"1474487","toID":"1474542","formEdgeID":null},{"edgeID":"1918280","fromID":"1474542","toID":"1215874","formEdgeID":null},{"edgeID":"1918281","fromID":"1474540","toID":"1474543","formEdgeID":null},{"edgeID":"1918282","fromID":"1474543","toID":"1474542","formEdgeID":null},{"edgeID":"1918283","fromID":"1474500","toID":"1474544","formEdgeID":null},{"edgeID":"1918284","fromID":"1474544","toID":"1474504","formEdgeID":null},{"edgeID":"1918285","fromID":"1474504","toID":"1474545","formEdgeID":null},{"edgeID":"1918286","fromID":"1474545","toID":"1474508","formEdgeID":null},{"edgeID":"1918287","fromID":"1474547","toID":"1474546","formEdgeID":null},{"edgeID":"1918288","fromID":"1474548","toID":"1474547","formEdgeID":null},{"edgeID":"1918289","fromID":"1474546","toID":"1474549","formEdgeID":null},{"edgeID":"1918290","fromID":"1474549","toID":"1215899","formEdgeID":null},{"edgeID":"1918291","fromID":"1474512","toID":"1474550","formEdgeID":null},{"edgeID":"1918292","fromID":"1474550","toID":"1474546","formEdgeID":null},{"edgeID":"1918293","fromID":"1474504","toID":"1474551","formEdgeID":null},{"edgeID":"1918294","fromID":"1474551","toID":"1474512","formEdgeID":null},{"edgeID":"1918295","fromID":"1474512","toID":"1474552","formEdgeID":null},{"edgeID":"1918296","fromID":"1474552","toID":"1474516","formEdgeID":null},{"edgeID":"1918297","fromID":"1474512","toID":"1474553","formEdgeID":null},{"edgeID":"1918298","fromID":"1474553","toID":"1474520","formEdgeID":null},{"edgeID":"1918299","fromID":"1215899","toID":"1474554","formEdgeID":null},{"edgeID":"1918300","fromID":"1474554","toID":"1215908","formEdgeID":null},{"edgeID":"1918301","fromID":"1474553","toID":"1474555","formEdgeID":null},{"edgeID":"1918302","fromID":"1474555","toID":"1474554","formEdgeID":null},{"edgeID":"1918303","fromID":"1215899","toID":"1474556","formEdgeID":null},{"edgeID":"1918304","fromID":"1474556","toID":"1215889","formEdgeID":null},{"edgeID":"1918305","fromID":"1474551","toID":"1474557","formEdgeID":null},{"edgeID":"1918306","fromID":"1474557","toID":"1474556","formEdgeID":null},{"edgeID":"1918307","fromID":"1474492","toID":"1474558","formEdgeID":null},{"edgeID":"1918308","fromID":"1474558","toID":"1215874","formEdgeID":null}],"locutions":[{"nodeID":"1474446","personID":"3837","timestamp":"2024-03-02 17:06:14","start":"2023-05-16 18:15:05","end":null,"source":null},{"nodeID":"1474450","personID":"3837","timestamp":"2024-03-02 17:06:14","start":"2023-05-16 18:15:11","end":null,"source":null},{"nodeID":"1474454","personID":"3837","timestamp":"2024-03-02 17:06:14","start":"2023-05-16 18:15:17","end":null,"source":null},{"nodeID":"1474459","personID":"3839","timestamp":"2024-03-02 17:06:14","start":"2023-05-16 18:15:20","end":null,"source":null},{"nodeID":"1474463","personID":"3839","timestamp":"2024-03-02 17:06:14","start":"2023-05-16 18:15:30","end":null,"source":null},{"nodeID":"1474467","personID":"3839","timestamp":"2024-03-02 17:06:14","start":"2023-05-16 18:15:31","end":null,"source":null},{"nodeID":"1474471","personID":"3839","timestamp":"2024-03-02 17:06:14","start":"2023-05-16 18:15:35","end":null,"source":null},{"nodeID":"1474475","personID":"3839","timestamp":"2024-03-02 17:06:14","start":"2023-05-16 18:15:40","end":null,"source":null},{"nodeID":"1474479","personID":"4054","timestamp":"2024-03-02 17:06:14","start":"2023-05-16 18:15:45","end":null,"source":null},{"nodeID":"1474483","personID":"4054","timestamp":"2024-03-02 17:06:14","start":"2023-05-16 18:15:47","end":null,"source":null},{"nodeID":"1474488","personID":"3837","timestamp":"2024-03-02 17:06:14","start":"2023-05-16 18:15:55","end":null,"source":null},{"nodeID":"1474492","personID":"3837","timestamp":"2024-03-02 17:06:14","start":"2023-05-16 18:15:59","end":null,"source":null},{"nodeID":"1474495","personID":"3837","timestamp":"2024-03-02 17:06:14","start":"2023-05-16 18:16:04","end":null,"source":null},{"nodeID":"1474500","personID":"4054","timestamp":"2024-03-02 17:06:14","start":"2023-05-16 18:16:11","end":null,"source":null},{"nodeID":"1474504","personID":"3837","timestamp":"2024-03-02 17:06:14","start":"2023-05-16 18:16:17","end":null,"source":null},{"nodeID":"1474508","personID":"3837","timestamp":"2024-03-02 17:06:14","start":"2023-05-16 18:16:19","end":null,"source":null},{"nodeID":"1474512","personID":"3837","timestamp":"2024-03-02 17:06:14","start":"2023-05-16 18:16:31","end":null,"source":null},{"nodeID":"1474516","personID":"3837","timestamp":"2024-03-02 17:06:14","start":"2023-05-16 18:16:39","end":null,"source":null},{"nodeID":"1474520","personID":"3837","timestamp":"2024-03-02 17:06:14","start":"2023-05-16 18:16:42","end":null,"source":null},{"nodeID":"1474546","personID":"7416","timestamp":"2024-03-02 17:06:14","start":null,"end":null,"source":null}]}