{"nodes":[{"nodeID":"1218334","text":"xxx is who left the matchbox and menu","type":"I","timestamp":"2023-08-31 21:34:07"},{"nodeID":"1218339","text":"Donna Goddard left the matchbox and menu","type":"I","timestamp":"2023-08-31 21:34:08"},{"nodeID":"1218347","text":"this meeting on the menu could have happened","type":"I","timestamp":"2023-08-31 21:34:08"},{"nodeID":"1218352","text":"the meeting was mentioned in Nick's notes","type":"I","timestamp":"2023-08-31 21:34:09"},{"nodeID":"1218365","text":"the meeting was not in Nick's notes","type":"I","timestamp":"2023-08-31 21:34:10"},{"nodeID":"1218373","text":"the meeting was in Carmen's notes","type":"I","timestamp":"2023-08-31 21:34:11"},{"nodeID":"1468532","text":"Female 2: who was that that left that","type":"L","timestamp":"2024-02-29 20:46:53"},{"nodeID":"1468533","text":"Analysing","type":"YA","timestamp":"2024-02-29 20:46:53","scheme":"Analysing","schemeID":"75"},{"nodeID":"1468534","text":"Anon: Female 2: who was that that left that","type":"L","timestamp":"2024-02-29 20:46:53"},{"nodeID":"1468535","text":"Pure Questioning","type":"YA","timestamp":"2024-02-29 20:46:53","scheme":"PureQuestioning","schemeID":"91"},{"nodeID":"1468536","text":"Female 1: Donna Goddard","type":"L","timestamp":"2024-02-29 20:46:54"},{"nodeID":"1468537","text":"Analysing","type":"YA","timestamp":"2024-02-29 20:46:54","scheme":"Analysing","schemeID":"75"},{"nodeID":"1468538","text":"Anon: Female 1: Donna Goddard","type":"L","timestamp":"2024-02-29 20:46:54"},{"nodeID":"1468539","text":"Asserting","type":"YA","timestamp":"2024-02-29 20:46:54","scheme":"Asserting","schemeID":"74"},{"nodeID":"1468540","text":"Default Rephrase","type":"MA","timestamp":"2024-02-29 20:46:54","scheme":"Default Rephrase","schemeID":"144"},{"nodeID":"1468541","text":"Default Transition","type":"TA","timestamp":"2024-02-29 20:46:54","scheme":"Default Transition","schemeID":"82"},{"nodeID":"1468542","text":"Default Illocuting","type":"YA","timestamp":"2024-02-29 20:46:54","scheme":"Default Illocuting","schemeID":"168"},{"nodeID":"1468543","text":"Female 2: this meeting on the menu, could have happened","type":"L","timestamp":"2024-02-29 20:46:55"},{"nodeID":"1468544","text":"Analysing","type":"YA","timestamp":"2024-02-29 20:46:55","scheme":"Analysing","schemeID":"75"},{"nodeID":"1468545","text":"Anon: Female 2: this meeting on the menu, could have happened","type":"L","timestamp":"2024-02-29 20:46:55"},{"nodeID":"1468546","text":"Assertive Questioning","type":"YA","timestamp":"2024-02-29 20:46:55","scheme":"AssertiveQuestioning","schemeID":"73"},{"nodeID":"1468547","text":"Female 2: that was his notes","type":"L","timestamp":"2024-02-29 20:46:55"},{"nodeID":"1468548","text":"Analysing","type":"YA","timestamp":"2024-02-29 20:46:55","scheme":"Analysing","schemeID":"75"},{"nodeID":"1468549","text":"Anon: Female 2: that was his notes","type":"L","timestamp":"2024-02-29 20:46:55"},{"nodeID":"1468550","text":"Asserting","type":"YA","timestamp":"2024-02-29 20:46:55","scheme":"Asserting","schemeID":"74"},{"nodeID":"1468551","text":"Default Inference","type":"RA","timestamp":"2024-02-29 20:46:55","scheme":"Default Inference","schemeID":"72"},{"nodeID":"1468552","text":"Default Transition","type":"TA","timestamp":"2024-02-29 20:46:55","scheme":"Default Transition","schemeID":"82"},{"nodeID":"1468553","text":"Arguing","type":"YA","timestamp":"2024-02-29 20:46:55","scheme":"Arguing","schemeID":"80"},{"nodeID":"1468554","text":"Female 3: No","type":"L","timestamp":"2024-02-29 20:46:55"},{"nodeID":"1468555","text":"Analysing","type":"YA","timestamp":"2024-02-29 20:46:55","scheme":"Analysing","schemeID":"75"},{"nodeID":"1468556","text":"Anon: Female 3: No","type":"L","timestamp":"2024-02-29 20:46:55"},{"nodeID":"1468557","text":"Default Transition","type":"TA","timestamp":"2024-02-29 20:46:55","scheme":"Default Transition","schemeID":"82"},{"nodeID":"1468558","text":"Disagreeing","type":"YA","timestamp":"2024-02-29 20:46:55","scheme":"Disagreeing","schemeID":"78"},{"nodeID":"1468559","text":"Female 3: this is not his notes","type":"L","timestamp":"2024-02-29 20:46:56"},{"nodeID":"1468560","text":"Analysing","type":"YA","timestamp":"2024-02-29 20:46:56","scheme":"Analysing","schemeID":"75"},{"nodeID":"1468561","text":"Anon: Female 3: this is not his notes","type":"L","timestamp":"2024-02-29 20:46:56"},{"nodeID":"1468562","text":"Asserting","type":"YA","timestamp":"2024-02-29 20:46:56","scheme":"Asserting","schemeID":"74"},{"nodeID":"1468563","text":"Default Conflict","type":"CA","timestamp":"2024-02-29 20:46:56","scheme":"Default Conflict","schemeID":"71"},{"nodeID":"1468564","text":"Default Transition","type":"TA","timestamp":"2024-02-29 20:46:56","scheme":"Default Transition","schemeID":"82"},{"nodeID":"1468565","text":"Disagreeing","type":"YA","timestamp":"2024-02-29 20:46:56","scheme":"Disagreeing","schemeID":"78"},{"nodeID":"1468566","text":"Female 1: This is like Carmen's notes","type":"L","timestamp":"2024-02-29 20:46:57"},{"nodeID":"1468567","text":"Analysing","type":"YA","timestamp":"2024-02-29 20:46:57","scheme":"Analysing","schemeID":"75"},{"nodeID":"1468568","text":"Anon: Female 1: This is like Carmen's notes","type":"L","timestamp":"2024-02-29 20:46:57"},{"nodeID":"1468569","text":"Hypothesising","type":"YA","timestamp":"2024-02-29 20:46:57","scheme":"Hypothesising","schemeID":"410"},{"nodeID":"1468570","text":"Default Inference","type":"RA","timestamp":"2024-02-29 20:46:57","scheme":"Default Inference","schemeID":"72"},{"nodeID":"1468571","text":"Default Transition","type":"TA","timestamp":"2024-02-29 20:46:57","scheme":"Default Transition","schemeID":"82"},{"nodeID":"1468572","text":"Arguing","type":"YA","timestamp":"2024-02-29 20:46:57","scheme":"Arguing","schemeID":"80"}],"edges":[{"edgeID":"1910471","fromID":"1468533","toID":"1468532","formEdgeID":null},{"edgeID":"1910472","fromID":"1468534","toID":"1468533","formEdgeID":null},{"edgeID":"1910473","fromID":"1468532","toID":"1468535","formEdgeID":null},{"edgeID":"1910474","fromID":"1468535","toID":"1218334","formEdgeID":null},{"edgeID":"1910475","fromID":"1468537","toID":"1468536","formEdgeID":null},{"edgeID":"1910476","fromID":"1468538","toID":"1468537","formEdgeID":null},{"edgeID":"1910477","fromID":"1468536","toID":"1468539","formEdgeID":null},{"edgeID":"1910478","fromID":"1468539","toID":"1218339","formEdgeID":null},{"edgeID":"1910479","fromID":"1218339","toID":"1468540","formEdgeID":null},{"edgeID":"1910480","fromID":"1468540","toID":"1218334","formEdgeID":null},{"edgeID":"1910481","fromID":"1468532","toID":"1468541","formEdgeID":null},{"edgeID":"1910482","fromID":"1468541","toID":"1468536","formEdgeID":null},{"edgeID":"1910483","fromID":"1468541","toID":"1468542","formEdgeID":null},{"edgeID":"1910484","fromID":"1468542","toID":"1468540","formEdgeID":null},{"edgeID":"1910485","fromID":"1468544","toID":"1468543","formEdgeID":null},{"edgeID":"1910486","fromID":"1468545","toID":"1468544","formEdgeID":null},{"edgeID":"1910487","fromID":"1468543","toID":"1468546","formEdgeID":null},{"edgeID":"1910488","fromID":"1468546","toID":"1218347","formEdgeID":null},{"edgeID":"1910489","fromID":"1468548","toID":"1468547","formEdgeID":null},{"edgeID":"1910490","fromID":"1468549","toID":"1468548","formEdgeID":null},{"edgeID":"1910491","fromID":"1468547","toID":"1468550","formEdgeID":null},{"edgeID":"1910492","fromID":"1468550","toID":"1218352","formEdgeID":null},{"edgeID":"1910493","fromID":"1218352","toID":"1468551","formEdgeID":null},{"edgeID":"1910494","fromID":"1468551","toID":"1218347","formEdgeID":null},{"edgeID":"1910495","fromID":"1468543","toID":"1468552","formEdgeID":null},{"edgeID":"1910496","fromID":"1468552","toID":"1468547","formEdgeID":null},{"edgeID":"1910497","fromID":"1468552","toID":"1468553","formEdgeID":null},{"edgeID":"1910498","fromID":"1468553","toID":"1468551","formEdgeID":null},{"edgeID":"1910499","fromID":"1468555","toID":"1468554","formEdgeID":null},{"edgeID":"1910500","fromID":"1468556","toID":"1468555","formEdgeID":null},{"edgeID":"1910501","fromID":"1468547","toID":"1468557","formEdgeID":null},{"edgeID":"1910502","fromID":"1468557","toID":"1468554","formEdgeID":null},{"edgeID":"1910503","fromID":"1468557","toID":"1468558","formEdgeID":null},{"edgeID":"1910504","fromID":"1468558","toID":"1218352","formEdgeID":null},{"edgeID":"1910505","fromID":"1468560","toID":"1468559","formEdgeID":null},{"edgeID":"1910506","fromID":"1468561","toID":"1468560","formEdgeID":null},{"edgeID":"1910507","fromID":"1468559","toID":"1468562","formEdgeID":null},{"edgeID":"1910508","fromID":"1468562","toID":"1218365","formEdgeID":null},{"edgeID":"1910509","fromID":"1218365","toID":"1468563","formEdgeID":null},{"edgeID":"1910510","fromID":"1468563","toID":"1218352","formEdgeID":null},{"edgeID":"1910511","fromID":"1468547","toID":"1468564","formEdgeID":null},{"edgeID":"1910512","fromID":"1468564","toID":"1468559","formEdgeID":null},{"edgeID":"1910513","fromID":"1468554","toID":"1468564","formEdgeID":null},{"edgeID":"1910514","fromID":"1468564","toID":"1468565","formEdgeID":null},{"edgeID":"1910515","fromID":"1468565","toID":"1468563","formEdgeID":null},{"edgeID":"1910516","fromID":"1468567","toID":"1468566","formEdgeID":null},{"edgeID":"1910517","fromID":"1468568","toID":"1468567","formEdgeID":null},{"edgeID":"1910518","fromID":"1468566","toID":"1468569","formEdgeID":null},{"edgeID":"1910519","fromID":"1468569","toID":"1218373","formEdgeID":null},{"edgeID":"1910520","fromID":"1218373","toID":"1468570","formEdgeID":null},{"edgeID":"1910521","fromID":"1468570","toID":"1218365","formEdgeID":null},{"edgeID":"1910522","fromID":"1468559","toID":"1468571","formEdgeID":null},{"edgeID":"1910523","fromID":"1468571","toID":"1468566","formEdgeID":null},{"edgeID":"1910524","fromID":"1468571","toID":"1468572","formEdgeID":null},{"edgeID":"1910525","fromID":"1468572","toID":"1468570","formEdgeID":null}],"locutions":[{"nodeID":"1468532","personID":"3837","timestamp":"2024-02-29 20:46:57","start":"2023-05-16 16:35:45","end":null,"source":null},{"nodeID":"1468536","personID":"4054","timestamp":"2024-02-29 20:46:57","start":"2023-05-16 16:35:50","end":null,"source":null},{"nodeID":"1468543","personID":"3837","timestamp":"2024-02-29 20:46:57","start":"2023-05-16 16:36:33","end":null,"source":null},{"nodeID":"1468547","personID":"3837","timestamp":"2024-02-29 20:46:57","start":"2023-05-16 16:36:34","end":null,"source":null},{"nodeID":"1468554","personID":"3839","timestamp":"2024-02-29 20:46:57","start":"2023-05-16 16:36:34","end":null,"source":null},{"nodeID":"1468559","personID":"3839","timestamp":"2024-02-29 20:46:57","start":"2023-05-16 16:36:35","end":null,"source":null},{"nodeID":"1468566","personID":"4054","timestamp":"2024-02-29 20:46:57","start":"2023-05-16 16:36:36","end":null,"source":null}]}