{"nodes":[{"nodeID":"1210899","text":"body found 6:47","type":"I","timestamp":"2023-08-24 20:09:00"},{"nodeID":"1210907","text":"7.29 coroner arrived","type":"I","timestamp":"2023-08-24 20:09:01"},{"nodeID":"1210913","text":"that would put the time of death between 5:29 and 6:29","type":"I","timestamp":"2023-08-24 20:09:01"},{"nodeID":"1210918","text":"the coroner arrived at xxx","type":"I","timestamp":"2023-08-24 20:09:02"},{"nodeID":"1210923","text":"the coroner arrived at seven twenty-nine","type":"I","timestamp":"2023-08-24 20:09:02"},{"nodeID":"1210939","text":"Nick left the pub","type":"I","timestamp":"2023-08-24 20:09:03"},{"nodeID":"1210944","text":"Nick was alive at 3:33","type":"I","timestamp":"2023-08-24 20:09:04"},{"nodeID":"1210949","text":"we've got quite a close window for Nick's death there","type":"I","timestamp":"2023-08-24 20:09:04"},{"nodeID":"1210960","text":"6:37, possible dead body called in, Devil's Well","type":"I","timestamp":"2023-08-24 20:09:04"},{"nodeID":"1210971","text":"Nick has probably been dead three to four hours","type":"I","timestamp":"2023-08-24 20:09:05"},{"nodeID":"1470671","text":"Female 3:  body found 6:47","type":"L","timestamp":"2024-03-01 17:03:31"},{"nodeID":"1470672","text":"Analysing","type":"YA","timestamp":"2024-03-01 17:03:31","scheme":"Analysing","schemeID":"75"},{"nodeID":"1470673","text":"Lara: Female 3:  body found 6:47","type":"L","timestamp":"2024-03-01 17:03:31"},{"nodeID":"1470674","text":"Asserting","type":"YA","timestamp":"2024-03-01 17:03:31","scheme":"Asserting","schemeID":"74"},{"nodeID":"1470675","text":"Female 1:  7.29 coroner arrived","type":"L","timestamp":"2024-03-01 17:03:31"},{"nodeID":"1470676","text":"Analysing","type":"YA","timestamp":"2024-03-01 17:03:31","scheme":"Analysing","schemeID":"75"},{"nodeID":"1470677","text":"Lara: Female 1:  7.29 coroner arrived","type":"L","timestamp":"2024-03-01 17:03:31"},{"nodeID":"1470678","text":"police report: 7.29 coroner arrived","type":"L","timestamp":"2024-03-01 17:03:32"},{"nodeID":"1470679","text":"Analysing","type":"YA","timestamp":"2024-03-01 17:03:32","scheme":"Analysing","schemeID":"75"},{"nodeID":"1470680","text":"Lara: police report: 7.29 coroner arrived","type":"L","timestamp":"2024-03-01 17:03:32"},{"nodeID":"1470681","text":"Asserting","type":"YA","timestamp":"2024-03-01 17:03:32","scheme":"Asserting","schemeID":"74"},{"nodeID":"1470682","text":"Asserting","type":"YA","timestamp":"2024-03-01 17:03:32","scheme":"Asserting","schemeID":"74"},{"nodeID":"1470683","text":"Female 1: that would put it between 5:29 and 6:29, the time of death","type":"L","timestamp":"2024-03-01 17:03:33"},{"nodeID":"1470684","text":"Analysing","type":"YA","timestamp":"2024-03-01 17:03:33","scheme":"Analysing","schemeID":"75"},{"nodeID":"1470685","text":"Lara: Female 1: that would put it between 5:29 and 6:29, the time of death","type":"L","timestamp":"2024-03-01 17:03:33"},{"nodeID":"1470686","text":"Assertive Questioning","type":"YA","timestamp":"2024-03-01 17:03:33","scheme":"AssertiveQuestioning","schemeID":"73"},{"nodeID":"1470687","text":"Female 3: when was it the coroner arrived","type":"L","timestamp":"2024-03-01 17:03:33"},{"nodeID":"1470688","text":"Analysing","type":"YA","timestamp":"2024-03-01 17:03:33","scheme":"Analysing","schemeID":"75"},{"nodeID":"1470689","text":"Lara: Female 3: when was it the coroner arrived","type":"L","timestamp":"2024-03-01 17:03:33"},{"nodeID":"1470690","text":"Pure Questioning","type":"YA","timestamp":"2024-03-01 17:03:33","scheme":"PureQuestioning","schemeID":"91"},{"nodeID":"1470691","text":"Female 1: Seven twenty-nine","type":"L","timestamp":"2024-03-01 17:03:34"},{"nodeID":"1470692","text":"Analysing","type":"YA","timestamp":"2024-03-01 17:03:34","scheme":"Analysing","schemeID":"75"},{"nodeID":"1470693","text":"Lara: Female 1: Seven twenty-nine","type":"L","timestamp":"2024-03-01 17:03:34"},{"nodeID":"1470694","text":"Asserting","type":"YA","timestamp":"2024-03-01 17:03:34","scheme":"Asserting","schemeID":"74"},{"nodeID":"1470695","text":"Female 3: 7:29","type":"L","timestamp":"2024-03-01 17:03:34"},{"nodeID":"1470696","text":"Analysing","type":"YA","timestamp":"2024-03-01 17:03:34","scheme":"Analysing","schemeID":"75"},{"nodeID":"1470697","text":"Lara: Female 3: 7:29","type":"L","timestamp":"2024-03-01 17:03:34"},{"nodeID":"1470698","text":"time of death is between 3:29 and 4:29","type":"I","timestamp":"2024-03-01 17:03:35"},{"nodeID":"1470699","text":"Female 3: time of death, we're thinking between 5:29, no sorry, between 3:29 and 4:29","type":"L","timestamp":"2024-03-01 17:03:35"},{"nodeID":"1470700","text":"Analysing","type":"YA","timestamp":"2024-03-01 17:03:35","scheme":"Analysing","schemeID":"75"},{"nodeID":"1470701","text":"Lara: Female 3: time of death, we're thinking between 5:29, no sorry, between 3:29 and 4:29","type":"L","timestamp":"2024-03-01 17:03:35"},{"nodeID":"1470702","text":"Hypothesising","type":"YA","timestamp":"2024-03-01 17:03:35","scheme":"Hypothesising","schemeID":"410"},{"nodeID":"1470703","text":"Female 2: Yeah, that's right","type":"L","timestamp":"2024-03-01 17:03:35"},{"nodeID":"1470704","text":"Analysing","type":"YA","timestamp":"2024-03-01 17:03:35","scheme":"Analysing","schemeID":"75"},{"nodeID":"1470705","text":"Lara: Female 2: Yeah, that's right","type":"L","timestamp":"2024-03-01 17:03:35"},{"nodeID":"1470706","text":"Female 2: he left the pub","type":"L","timestamp":"2024-03-01 17:03:35"},{"nodeID":"1470707","text":"Analysing","type":"YA","timestamp":"2024-03-01 17:03:35","scheme":"Analysing","schemeID":"75"},{"nodeID":"1470708","text":"Lara: Female 2: he left the pub","type":"L","timestamp":"2024-03-01 17:03:35"},{"nodeID":"1470709","text":"Asserting","type":"YA","timestamp":"2024-03-01 17:03:35","scheme":"Asserting","schemeID":"74"},{"nodeID":"1470710","text":"Female 2: he was alive at 3:33","type":"L","timestamp":"2024-03-01 17:03:36"},{"nodeID":"1470711","text":"Analysing","type":"YA","timestamp":"2024-03-01 17:03:36","scheme":"Analysing","schemeID":"75"},{"nodeID":"1470712","text":"Lara: Female 2: he was alive at 3:33","type":"L","timestamp":"2024-03-01 17:03:36"},{"nodeID":"1470713","text":"Asserting","type":"YA","timestamp":"2024-03-01 17:03:36","scheme":"Asserting","schemeID":"74"},{"nodeID":"1470714","text":"Female 2: we've got quite a close window for his death there","type":"L","timestamp":"2024-03-01 17:03:37"},{"nodeID":"1470715","text":"Analysing","type":"YA","timestamp":"2024-03-01 17:03:37","scheme":"Analysing","schemeID":"75"},{"nodeID":"1470716","text":"Lara: Female 2: we've got quite a close window for his death there","type":"L","timestamp":"2024-03-01 17:03:37"},{"nodeID":"1470717","text":"Asserting","type":"YA","timestamp":"2024-03-01 17:03:37","scheme":"Asserting","schemeID":"74"},{"nodeID":"1470718","text":"Female 1: Yeah","type":"L","timestamp":"2024-03-01 17:03:37"},{"nodeID":"1470719","text":"Analysing","type":"YA","timestamp":"2024-03-01 17:03:37","scheme":"Analysing","schemeID":"75"},{"nodeID":"1470720","text":"Lara: Female 1: Yeah","type":"L","timestamp":"2024-03-01 17:03:37"},{"nodeID":"1470721","text":"Female 1: 6:37, possible dead body called in, Devil's Well","type":"L","timestamp":"2024-03-01 17:03:37"},{"nodeID":"1470722","text":"Analysing","type":"YA","timestamp":"2024-03-01 17:03:37","scheme":"Analysing","schemeID":"75"},{"nodeID":"1470723","text":"Lara: Female 1: 6:37, possible dead body called in, Devil's Well","type":"L","timestamp":"2024-03-01 17:03:37"},{"nodeID":"1470724","text":"police report: 6:37, possible dead body called in, Devil's Well","type":"L","timestamp":"2024-03-01 17:03:37"},{"nodeID":"1470725","text":"Analysing","type":"YA","timestamp":"2024-03-01 17:03:37","scheme":"Analysing","schemeID":"75"},{"nodeID":"1470726","text":"Lara: police report: 6:37, possible dead body called in, Devil's Well","type":"L","timestamp":"2024-03-01 17:03:37"},{"nodeID":"1470727","text":"Asserting","type":"YA","timestamp":"2024-03-01 17:03:37","scheme":"Asserting","schemeID":"74"},{"nodeID":"1470728","text":"Asserting","type":"YA","timestamp":"2024-03-01 17:03:37","scheme":"Asserting","schemeID":"74"},{"nodeID":"1470729","text":"Default Transition","type":"TA","timestamp":"2024-03-01 17:03:37","scheme":"Default Transition","schemeID":"82"},{"nodeID":"1470730","text":"Default Transition","type":"TA","timestamp":"2024-03-01 17:03:37","scheme":"Default Transition","schemeID":"82"},{"nodeID":"1470731","text":"Female 1: says he's probably been dead three to four hours","type":"L","timestamp":"2024-03-01 17:03:37"},{"nodeID":"1470732","text":"Analysing","type":"YA","timestamp":"2024-03-01 17:03:37","scheme":"Analysing","schemeID":"75"},{"nodeID":"1470733","text":"Lara: Female 1: says he's probably been dead three to four hours","type":"L","timestamp":"2024-03-01 17:03:37"},{"nodeID":"1470734","text":"the coroner: Nick has probably been dead three to four hours","type":"L","timestamp":"2024-03-01 17:03:38"},{"nodeID":"1470735","text":"Analysing","type":"YA","timestamp":"2024-03-01 17:03:38","scheme":"Analysing","schemeID":"75"},{"nodeID":"1470736","text":"Lara: the coroner: he's probably been dead three to four hours","type":"L","timestamp":"2024-03-01 17:03:38"},{"nodeID":"1470737","text":"Asserting","type":"YA","timestamp":"2024-03-01 17:03:38","scheme":"Asserting","schemeID":"74"},{"nodeID":"1470738","text":"Asserting","type":"YA","timestamp":"2024-03-01 17:03:38","scheme":"Asserting","schemeID":"74"},{"nodeID":"1470739","text":"Default Transition","type":"TA","timestamp":"2024-03-01 17:03:38","scheme":"Default Transition","schemeID":"82"},{"nodeID":"1470740","text":"Default Transition","type":"TA","timestamp":"2024-03-01 17:03:38","scheme":"Default Transition","schemeID":"82"},{"nodeID":"1470741","text":"Default Inference","type":"RA","timestamp":"2024-03-01 17:03:38","scheme":"Default Inference","schemeID":"72"},{"nodeID":"1470742","text":"Arguing","type":"YA","timestamp":"2024-03-01 17:03:38","scheme":"Arguing","schemeID":"80"},{"nodeID":"1470743","text":"Default Transition","type":"TA","timestamp":"2024-03-01 17:03:38","scheme":"Default Transition","schemeID":"82"},{"nodeID":"1470744","text":"Default Transition","type":"TA","timestamp":"2024-03-01 17:03:38","scheme":"Default Transition","schemeID":"82"},{"nodeID":"1470745","text":"Default Rephrase","type":"MA","timestamp":"2024-03-01 17:03:38","scheme":"Default Rephrase","schemeID":"144"},{"nodeID":"1470746","text":"Default Illocuting","type":"YA","timestamp":"2024-03-01 17:03:38","scheme":"Default Illocuting","schemeID":"168"},{"nodeID":"1470747","text":"Default Transition","type":"TA","timestamp":"2024-03-01 17:03:38","scheme":"Default Transition","schemeID":"82"},{"nodeID":"1470748","text":"Asserting","type":"YA","timestamp":"2024-03-01 17:03:38","scheme":"Asserting","schemeID":"74"},{"nodeID":"1470749","text":"Default Transition","type":"TA","timestamp":"2024-03-01 17:03:38","scheme":"Default Transition","schemeID":"82"},{"nodeID":"1470750","text":"Default Conflict","type":"CA","timestamp":"2024-03-01 17:03:38","scheme":"Default Conflict","schemeID":"71"},{"nodeID":"1470751","text":"Disagreeing","type":"YA","timestamp":"2024-03-01 17:03:38","scheme":"Disagreeing","schemeID":"78"},{"nodeID":"1470752","text":"Default Transition","type":"TA","timestamp":"2024-03-01 17:03:38","scheme":"Default Transition","schemeID":"82"},{"nodeID":"1470753","text":"Agreeing","type":"YA","timestamp":"2024-03-01 17:03:38","scheme":"Agreeing","schemeID":"77"},{"nodeID":"1470754","text":"Default Transition","type":"TA","timestamp":"2024-03-01 17:03:38","scheme":"Default Transition","schemeID":"82"},{"nodeID":"1470755","text":"Default Inference","type":"RA","timestamp":"2024-03-01 17:03:38","scheme":"Default Inference","schemeID":"72"},{"nodeID":"1470756","text":"Arguing","type":"YA","timestamp":"2024-03-01 17:03:38","scheme":"Arguing","schemeID":"80"},{"nodeID":"1470757","text":"Default Transition","type":"TA","timestamp":"2024-03-01 17:03:38","scheme":"Default Transition","schemeID":"82"},{"nodeID":"1470758","text":"Default Inference","type":"RA","timestamp":"2024-03-01 17:03:38","scheme":"Default Inference","schemeID":"72"},{"nodeID":"1470759","text":"Arguing","type":"YA","timestamp":"2024-03-01 17:03:38","scheme":"Arguing","schemeID":"80"},{"nodeID":"1470760","text":"Default Transition","type":"TA","timestamp":"2024-03-01 17:03:38","scheme":"Default Transition","schemeID":"82"},{"nodeID":"1470761","text":"Agreeing","type":"YA","timestamp":"2024-03-01 17:03:38","scheme":"Agreeing","schemeID":"77"},{"nodeID":"1470762","text":"Default Transition","type":"TA","timestamp":"2024-03-01 17:03:38","scheme":"Default Transition","schemeID":"82"},{"nodeID":"1470763","text":"Default Rephrase","type":"MA","timestamp":"2024-03-01 17:03:38","scheme":"Default Rephrase","schemeID":"144"},{"nodeID":"1470764","text":"Restating","type":"YA","timestamp":"2024-03-01 17:03:38","scheme":"Restating","schemeID":"101"}],"edges":[{"edgeID":"1913245","fromID":"1470672","toID":"1470671","formEdgeID":null},{"edgeID":"1913246","fromID":"1470673","toID":"1470672","formEdgeID":null},{"edgeID":"1913247","fromID":"1470671","toID":"1470674","formEdgeID":null},{"edgeID":"1913248","fromID":"1470674","toID":"1210899","formEdgeID":null},{"edgeID":"1913249","fromID":"1470676","toID":"1470675","formEdgeID":null},{"edgeID":"1913250","fromID":"1470677","toID":"1470676","formEdgeID":null},{"edgeID":"1913251","fromID":"1470679","toID":"1470678","formEdgeID":null},{"edgeID":"1913252","fromID":"1470680","toID":"1470679","formEdgeID":null},{"edgeID":"1913253","fromID":"1470678","toID":"1470681","formEdgeID":null},{"edgeID":"1913254","fromID":"1470681","toID":"1210907","formEdgeID":null},{"edgeID":"1913255","fromID":"1470675","toID":"1470682","formEdgeID":null},{"edgeID":"1913256","fromID":"1470682","toID":"1470678","formEdgeID":null},{"edgeID":"1913257","fromID":"1470684","toID":"1470683","formEdgeID":null},{"edgeID":"1913258","fromID":"1470685","toID":"1470684","formEdgeID":null},{"edgeID":"1913259","fromID":"1470683","toID":"1470686","formEdgeID":null},{"edgeID":"1913260","fromID":"1470686","toID":"1210913","formEdgeID":null},{"edgeID":"1913261","fromID":"1470688","toID":"1470687","formEdgeID":null},{"edgeID":"1913262","fromID":"1470689","toID":"1470688","formEdgeID":null},{"edgeID":"1913263","fromID":"1470687","toID":"1470690","formEdgeID":null},{"edgeID":"1913264","fromID":"1470690","toID":"1210918","formEdgeID":null},{"edgeID":"1913265","fromID":"1470692","toID":"1470691","formEdgeID":null},{"edgeID":"1913266","fromID":"1470693","toID":"1470692","formEdgeID":null},{"edgeID":"1913267","fromID":"1470691","toID":"1470694","formEdgeID":null},{"edgeID":"1913268","fromID":"1470694","toID":"1210923","formEdgeID":null},{"edgeID":"1913269","fromID":"1470696","toID":"1470695","formEdgeID":null},{"edgeID":"1913270","fromID":"1470697","toID":"1470696","formEdgeID":null},{"edgeID":"1913271","fromID":"1470700","toID":"1470699","formEdgeID":null},{"edgeID":"1913272","fromID":"1470701","toID":"1470700","formEdgeID":null},{"edgeID":"1913273","fromID":"1470699","toID":"1470702","formEdgeID":null},{"edgeID":"1913274","fromID":"1470702","toID":"1470698","formEdgeID":null},{"edgeID":"1913275","fromID":"1470704","toID":"1470703","formEdgeID":null},{"edgeID":"1913276","fromID":"1470705","toID":"1470704","formEdgeID":null},{"edgeID":"1913277","fromID":"1470707","toID":"1470706","formEdgeID":null},{"edgeID":"1913278","fromID":"1470708","toID":"1470707","formEdgeID":null},{"edgeID":"1913279","fromID":"1470706","toID":"1470709","formEdgeID":null},{"edgeID":"1913280","fromID":"1470709","toID":"1210939","formEdgeID":null},{"edgeID":"1913281","fromID":"1470711","toID":"1470710","formEdgeID":null},{"edgeID":"1913282","fromID":"1470712","toID":"1470711","formEdgeID":null},{"edgeID":"1913283","fromID":"1470710","toID":"1470713","formEdgeID":null},{"edgeID":"1913284","fromID":"1470713","toID":"1210944","formEdgeID":null},{"edgeID":"1913285","fromID":"1470715","toID":"1470714","formEdgeID":null},{"edgeID":"1913286","fromID":"1470716","toID":"1470715","formEdgeID":null},{"edgeID":"1913287","fromID":"1470714","toID":"1470717","formEdgeID":null},{"edgeID":"1913288","fromID":"1470717","toID":"1210949","formEdgeID":null},{"edgeID":"1913289","fromID":"1470719","toID":"1470718","formEdgeID":null},{"edgeID":"1913290","fromID":"1470720","toID":"1470719","formEdgeID":null},{"edgeID":"1913291","fromID":"1470722","toID":"1470721","formEdgeID":null},{"edgeID":"1913292","fromID":"1470723","toID":"1470722","formEdgeID":null},{"edgeID":"1913293","fromID":"1470725","toID":"1470724","formEdgeID":null},{"edgeID":"1913294","fromID":"1470726","toID":"1470725","formEdgeID":null},{"edgeID":"1913295","fromID":"1470724","toID":"1470727","formEdgeID":null},{"edgeID":"1913296","fromID":"1470727","toID":"1210960","formEdgeID":null},{"edgeID":"1913297","fromID":"1470721","toID":"1470728","formEdgeID":null},{"edgeID":"1913298","fromID":"1470728","toID":"1470724","formEdgeID":null},{"edgeID":"1913299","fromID":"1470721","toID":"1470729","formEdgeID":null},{"edgeID":"1913300","fromID":"1470729","toID":"1470671","formEdgeID":null},{"edgeID":"1913301","fromID":"1470721","toID":"1470730","formEdgeID":null},{"edgeID":"1913302","fromID":"1470730","toID":"1470675","formEdgeID":null},{"edgeID":"1913303","fromID":"1470732","toID":"1470731","formEdgeID":null},{"edgeID":"1913304","fromID":"1470733","toID":"1470732","formEdgeID":null},{"edgeID":"1913305","fromID":"1470735","toID":"1470734","formEdgeID":null},{"edgeID":"1913306","fromID":"1470736","toID":"1470735","formEdgeID":null},{"edgeID":"1913307","fromID":"1470734","toID":"1470737","formEdgeID":null},{"edgeID":"1913308","fromID":"1470737","toID":"1210971","formEdgeID":null},{"edgeID":"1913309","fromID":"1470731","toID":"1470738","formEdgeID":null},{"edgeID":"1913310","fromID":"1470738","toID":"1470734","formEdgeID":null},{"edgeID":"1913311","fromID":"1470675","toID":"1470739","formEdgeID":null},{"edgeID":"1913312","fromID":"1470739","toID":"1470731","formEdgeID":null},{"edgeID":"1913313","fromID":"1470731","toID":"1470740","formEdgeID":null},{"edgeID":"1913314","fromID":"1470740","toID":"1470683","formEdgeID":null},{"edgeID":"1913315","fromID":"1210971","toID":"1470741","formEdgeID":null},{"edgeID":"1913316","fromID":"1470741","toID":"1210913","formEdgeID":null},{"edgeID":"1913317","fromID":"1470740","toID":"1470742","formEdgeID":null},{"edgeID":"1913318","fromID":"1470742","toID":"1470741","formEdgeID":null},{"edgeID":"1913319","fromID":"1470675","toID":"1470743","formEdgeID":null},{"edgeID":"1913320","fromID":"1470743","toID":"1470687","formEdgeID":null},{"edgeID":"1913321","fromID":"1470687","toID":"1470744","formEdgeID":null},{"edgeID":"1913322","fromID":"1470744","toID":"1470691","formEdgeID":null},{"edgeID":"1913323","fromID":"1210923","toID":"1470745","formEdgeID":null},{"edgeID":"1913324","fromID":"1470745","toID":"1210918","formEdgeID":null},{"edgeID":"1913325","fromID":"1470744","toID":"1470746","formEdgeID":null},{"edgeID":"1913326","fromID":"1470746","toID":"1470745","formEdgeID":null},{"edgeID":"1913327","fromID":"1470691","toID":"1470747","formEdgeID":null},{"edgeID":"1913328","fromID":"1470747","toID":"1470695","formEdgeID":null},{"edgeID":"1913329","fromID":"1470695","toID":"1470748","formEdgeID":null},{"edgeID":"1913330","fromID":"1470748","toID":"1210923","formEdgeID":null},{"edgeID":"1913331","fromID":"1470683","toID":"1470749","formEdgeID":null},{"edgeID":"1913332","fromID":"1470749","toID":"1470699","formEdgeID":null},{"edgeID":"1913333","fromID":"1470698","toID":"1470750","formEdgeID":null},{"edgeID":"1913334","fromID":"1470750","toID":"1210913","formEdgeID":null},{"edgeID":"1913335","fromID":"1470749","toID":"1470751","formEdgeID":null},{"edgeID":"1913336","fromID":"1470751","toID":"1470750","formEdgeID":null},{"edgeID":"1913337","fromID":"1470699","toID":"1470752","formEdgeID":null},{"edgeID":"1913338","fromID":"1470752","toID":"1470703","formEdgeID":null},{"edgeID":"1913339","fromID":"1470752","toID":"1470753","formEdgeID":null},{"edgeID":"1913340","fromID":"1470753","toID":"1470698","formEdgeID":null},{"edgeID":"1913341","fromID":"1470706","toID":"1470754","formEdgeID":null},{"edgeID":"1913342","fromID":"1470754","toID":"1470710","formEdgeID":null},{"edgeID":"1913343","fromID":"1210939","toID":"1470755","formEdgeID":null},{"edgeID":"1913344","fromID":"1470755","toID":"1210944","formEdgeID":null},{"edgeID":"1913345","fromID":"1470754","toID":"1470756","formEdgeID":null},{"edgeID":"1913346","fromID":"1470756","toID":"1470755","formEdgeID":null},{"edgeID":"1913347","fromID":"1470710","toID":"1470757","formEdgeID":null},{"edgeID":"1913348","fromID":"1470757","toID":"1470714","formEdgeID":null},{"edgeID":"1913349","fromID":"1470699","toID":"1470757","formEdgeID":null},{"edgeID":"1913350","fromID":"1470698","toID":"1470758","formEdgeID":null},{"edgeID":"1913351","fromID":"1470758","toID":"1210949","formEdgeID":null},{"edgeID":"1913352","fromID":"1210944","toID":"1470758","formEdgeID":null},{"edgeID":"1913353","fromID":"1470757","toID":"1470759","formEdgeID":null},{"edgeID":"1913354","fromID":"1470759","toID":"1470758","formEdgeID":null},{"edgeID":"1913355","fromID":"1470714","toID":"1470760","formEdgeID":null},{"edgeID":"1913356","fromID":"1470760","toID":"1470718","formEdgeID":null},{"edgeID":"1913357","fromID":"1470760","toID":"1470761","formEdgeID":null},{"edgeID":"1913358","fromID":"1470761","toID":"1210949","formEdgeID":null},{"edgeID":"1913359","fromID":"1470695","toID":"1470762","formEdgeID":null},{"edgeID":"1913360","fromID":"1470762","toID":"1470699","formEdgeID":null},{"edgeID":"1913361","fromID":"1210899","toID":"1470763","formEdgeID":null},{"edgeID":"1913362","fromID":"1470763","toID":"1210960","formEdgeID":null},{"edgeID":"1913363","fromID":"1470729","toID":"1470764","formEdgeID":null},{"edgeID":"1913364","fromID":"1470764","toID":"1470763","formEdgeID":null}],"locutions":[{"nodeID":"1470671","personID":"3839","timestamp":"2024-03-01 17:03:38","start":"2023-05-16 16:52:34","end":null,"source":null},{"nodeID":"1470675","personID":"4054","timestamp":"2024-03-01 17:03:38","start":"2023-05-16 16:52:39","end":null,"source":null},{"nodeID":"1470678","personID":"7497","timestamp":"2024-03-01 17:03:38","start":"2023-05-16 16:52:39","end":null,"source":null},{"nodeID":"1470683","personID":"4054","timestamp":"2024-03-01 17:03:38","start":"2023-05-16 16:52:49","end":null,"source":null},{"nodeID":"1470687","personID":"3839","timestamp":"2024-03-01 17:03:38","start":"2023-05-16 16:52:54","end":null,"source":null},{"nodeID":"1470691","personID":"4054","timestamp":"2024-03-01 17:03:38","start":"2023-05-16 16:52:55","end":null,"source":null},{"nodeID":"1470695","personID":"3839","timestamp":"2024-03-01 17:03:38","start":"2023-05-16 16:52:57","end":null,"source":null},{"nodeID":"1470699","personID":"3839","timestamp":"2024-03-01 17:03:38","start":"2023-05-16 16:53:00","end":null,"source":null},{"nodeID":"1470703","personID":"3837","timestamp":"2024-03-01 17:03:38","start":"2023-05-16 16:53:03","end":null,"source":null},{"nodeID":"1470706","personID":"3837","timestamp":"2024-03-01 17:03:38","start":"2023-05-16 16:53:10","end":null,"source":null},{"nodeID":"1470710","personID":"3837","timestamp":"2024-03-01 17:03:38","start":"2023-05-16 16:53:11","end":null,"source":null},{"nodeID":"1470714","personID":"3837","timestamp":"2024-03-01 17:03:38","start":"2023-05-16 16:53:15","end":null,"source":null},{"nodeID":"1470718","personID":"4054","timestamp":"2024-03-01 17:03:38","start":"2023-05-16 16:53:15","end":null,"source":null},{"nodeID":"1470721","personID":"4054","timestamp":"2024-03-01 17:03:38","start":"2023-05-16 16:52:16","end":null,"source":null},{"nodeID":"1470724","personID":"7497","timestamp":"2024-03-01 17:03:38","start":"2023-05-16 16:52:16","end":null,"source":null},{"nodeID":"1470731","personID":"4054","timestamp":"2024-03-01 17:03:38","start":"2023-05-16 16:52:43","end":null,"source":null},{"nodeID":"1470734","personID":"6875","timestamp":"2024-03-01 17:03:38","start":"2023-05-16 16:52:43","end":null,"source":null}]}