{"nodes":[{"nodeID":"1209990","text":"funny how similar it is","type":"I","timestamp":"2023-08-24 19:03:43"},{"nodeID":"1209991","text":"Female 2: funny how similar it is","type":"L","timestamp":"2023-08-24 19:03:43"},{"nodeID":"1209992","text":"Analysing","type":"YA","timestamp":"2023-08-24 19:03:43","scheme":"Analysing","schemeID":"75"},{"nodeID":"1209993","text":"Anon: Female 2: funny how similar it is","type":"L","timestamp":"2023-08-24 19:03:43"},{"nodeID":"1209994","text":"Asserting","type":"YA","timestamp":"2023-08-24 19:03:43","scheme":"Asserting","schemeID":"74"},{"nodeID":"1209995","text":"Female 1: Yeah, very similar","type":"L","timestamp":"2023-08-24 19:03:43"},{"nodeID":"1209996","text":"Analysing","type":"YA","timestamp":"2023-08-24 19:03:43","scheme":"Analysing","schemeID":"75"},{"nodeID":"1209997","text":"Anon: Female 1: Yeah, very similar","type":"L","timestamp":"2023-08-24 19:03:43"},{"nodeID":"1209998","text":"Default Transition","type":"TA","timestamp":"2023-08-24 19:03:43","scheme":"Default Transition","schemeID":"82"},{"nodeID":"1209999","text":"Agreeing","type":"YA","timestamp":"2023-08-24 19:03:43","scheme":"Agreeing","schemeID":"77"},{"nodeID":"1210000","text":"the coroner and the deputy sheriff repeated almost like the same information on their reports","type":"I","timestamp":"2023-08-24 19:03:44"},{"nodeID":"1210001","text":"Female 3: they repeated almost like the same","type":"L","timestamp":"2023-08-24 19:03:44"},{"nodeID":"1210002","text":"Analysing","type":"YA","timestamp":"2023-08-24 19:03:44","scheme":"Analysing","schemeID":"75"},{"nodeID":"1210003","text":"Anon: Female 3: they repeated almost like the same","type":"L","timestamp":"2023-08-24 19:03:44"},{"nodeID":"1210004","text":"Asserting","type":"YA","timestamp":"2023-08-24 19:03:44","scheme":"Asserting","schemeID":"74"},{"nodeID":"1210005","text":"Default Transition","type":"TA","timestamp":"2023-08-24 19:03:44","scheme":"Default Transition","schemeID":"82"},{"nodeID":"1210006","text":"the stories of Nick being tipsy are slightly similar","type":"I","timestamp":"2023-08-24 19:03:44"},{"nodeID":"1210007","text":"Female 2: slightly","type":"L","timestamp":"2023-08-24 19:03:44"},{"nodeID":"1210008","text":"Analysing","type":"YA","timestamp":"2023-08-24 19:03:44","scheme":"Analysing","schemeID":"75"},{"nodeID":"1210009","text":"Anon: Female 2: slightly","type":"L","timestamp":"2023-08-24 19:03:44"},{"nodeID":"1210010","text":"Asserting","type":"YA","timestamp":"2023-08-24 19:03:44","scheme":"Asserting","schemeID":"74"},{"nodeID":"1210011","text":"the stories of Nick being tipsy are not quite the same story","type":"I","timestamp":"2023-08-24 19:03:45"},{"nodeID":"1210012","text":"Female 2: it's not quite the same story","type":"L","timestamp":"2023-08-24 19:03:45"},{"nodeID":"1210013","text":"Analysing","type":"YA","timestamp":"2023-08-24 19:03:45","scheme":"Analysing","schemeID":"75"},{"nodeID":"1210014","text":"Anon: Female 2: it's not quite the same story","type":"L","timestamp":"2023-08-24 19:03:45"},{"nodeID":"1210015","text":"Asserting","type":"YA","timestamp":"2023-08-24 19:03:45","scheme":"Asserting","schemeID":"74"},{"nodeID":"1210016","text":"Default Inference","type":"RA","timestamp":"2023-08-24 19:03:45","scheme":"Default Inference","schemeID":"72"},{"nodeID":"1210017","text":"Default Conflict","type":"CA","timestamp":"2023-08-24 19:03:45","scheme":"Default Conflict","schemeID":"71"},{"nodeID":"1210018","text":"Default Transition","type":"TA","timestamp":"2023-08-24 19:03:45","scheme":"Default Transition","schemeID":"82"},{"nodeID":"1210019","text":"Disagreeing","type":"YA","timestamp":"2023-08-24 19:03:45","scheme":"Disagreeing","schemeID":"78"},{"nodeID":"1210020","text":"Default Transition","type":"TA","timestamp":"2023-08-24 19:03:45","scheme":"Default Transition","schemeID":"82"},{"nodeID":"1210021","text":"Arguing","type":"YA","timestamp":"2023-08-24 19:03:45","scheme":"Arguing","schemeID":"80"},{"nodeID":"1210022","text":"there is some inconsistency in the stories","type":"I","timestamp":"2023-08-24 19:03:45"},{"nodeID":"1210023","text":"Female 2: I was just thinking the inconsistency","type":"L","timestamp":"2023-08-24 19:03:45"},{"nodeID":"1210024","text":"Analysing","type":"YA","timestamp":"2023-08-24 19:03:45","scheme":"Analysing","schemeID":"75"},{"nodeID":"1210025","text":"Anon: Female 2: I was just thinking the inconsistency","type":"L","timestamp":"2023-08-24 19:03:45"},{"nodeID":"1210026","text":"Asserting","type":"YA","timestamp":"2023-08-24 19:03:45","scheme":"Asserting","schemeID":"74"},{"nodeID":"1210027","text":"Default Inference","type":"RA","timestamp":"2023-08-24 19:03:45","scheme":"Default Inference","schemeID":"72"},{"nodeID":"1210028","text":"Default Transition","type":"TA","timestamp":"2023-08-24 19:03:45","scheme":"Default Transition","schemeID":"82"},{"nodeID":"1210029","text":"Arguing","type":"YA","timestamp":"2023-08-24 19:03:45","scheme":"Arguing","schemeID":"80"},{"nodeID":"1210030","text":"Cherie is the wife of Nick","type":"I","timestamp":"2023-08-24 19:03:46"},{"nodeID":"1210031","text":"Female 3: Wife","type":"L","timestamp":"2023-08-24 19:03:46"},{"nodeID":"1210032","text":"Analysing","type":"YA","timestamp":"2023-08-24 19:03:46","scheme":"Analysing","schemeID":"75"},{"nodeID":"1210033","text":"Anon: Female 3: Wife","type":"L","timestamp":"2023-08-24 19:03:46"},{"nodeID":"1210034","text":"Asserting","type":"YA","timestamp":"2023-08-24 19:03:46","scheme":"Asserting","schemeID":"74"},{"nodeID":"1210035","text":"Female 1: Is the wife of Nick Webster","type":"L","timestamp":"2023-08-24 19:03:46"},{"nodeID":"1210036","text":"Analysing","type":"YA","timestamp":"2023-08-24 19:03:46","scheme":"Analysing","schemeID":"75"},{"nodeID":"1210037","text":"Anon: Female 1: Is the wife of Nick Webster","type":"L","timestamp":"2023-08-24 19:03:46"},{"nodeID":"1210038","text":"Default Transition","type":"TA","timestamp":"2023-08-24 19:03:46","scheme":"Default Transition","schemeID":"82"},{"nodeID":"1210039","text":"Asserting","type":"YA","timestamp":"2023-08-24 19:03:46","scheme":"Asserting","schemeID":"74"},{"nodeID":"1210040","text":"Carmen took the letter out or did Chris gave it to her","type":"I","timestamp":"2023-08-24 19:03:46"},{"nodeID":"1210041","text":"Female 2: Did she take it out, or did he give it to her","type":"L","timestamp":"2023-08-24 19:03:46"},{"nodeID":"1210042","text":"Analysing","type":"YA","timestamp":"2023-08-24 19:03:46","scheme":"Analysing","schemeID":"75"},{"nodeID":"1210043","text":"Anon: Female 2: Did she take it out, or did he give it to her","type":"L","timestamp":"2023-08-24 19:03:46"},{"nodeID":"1210044","text":"Pure Questioning","type":"YA","timestamp":"2023-08-24 19:03:46","scheme":"PureQuestioning","schemeID":"91"},{"nodeID":"1210045","text":"Carmen stole the letter","type":"I","timestamp":"2023-08-24 19:03:47"},{"nodeID":"1210046","text":"Female 1: She stole it","type":"L","timestamp":"2023-08-24 19:03:47"},{"nodeID":"1210047","text":"Analysing","type":"YA","timestamp":"2023-08-24 19:03:47","scheme":"Analysing","schemeID":"75"},{"nodeID":"1210048","text":"Anon: Female 1: She stole it","type":"L","timestamp":"2023-08-24 19:03:47"},{"nodeID":"1210049","text":"Asserting","type":"YA","timestamp":"2023-08-24 19:03:47","scheme":"Asserting","schemeID":"74"},{"nodeID":"1210050","text":"Default Rephrase","type":"MA","timestamp":"2023-08-24 19:03:47","scheme":"Default Rephrase","schemeID":"144"},{"nodeID":"1210051","text":"Default Transition","type":"TA","timestamp":"2023-08-24 19:03:47","scheme":"Default Transition","schemeID":"82"},{"nodeID":"1210052","text":"Default Illocuting","type":"YA","timestamp":"2023-08-24 19:03:47","scheme":"Default Illocuting","schemeID":"168"},{"nodeID":"1210053","text":"Female 2: Okay, yeah","type":"L","timestamp":"2023-08-24 19:03:47"},{"nodeID":"1210054","text":"Analysing","type":"YA","timestamp":"2023-08-24 19:03:47","scheme":"Analysing","schemeID":"75"},{"nodeID":"1210055","text":"Anon: Female 2: Okay, yeah","type":"L","timestamp":"2023-08-24 19:03:47"},{"nodeID":"1210056","text":"Default Transition","type":"TA","timestamp":"2023-08-24 19:03:47","scheme":"Default Transition","schemeID":"82"},{"nodeID":"1210057","text":"Agreeing","type":"YA","timestamp":"2023-08-24 19:03:47","scheme":"Agreeing","schemeID":"77"}],"edges":[{"edgeID":"1594013","fromID":"1209992","toID":"1209991","formEdgeID":null},{"edgeID":"1594014","fromID":"1209993","toID":"1209992","formEdgeID":null},{"edgeID":"1594015","fromID":"1209991","toID":"1209994","formEdgeID":null},{"edgeID":"1594016","fromID":"1209994","toID":"1209990","formEdgeID":null},{"edgeID":"1594017","fromID":"1209996","toID":"1209995","formEdgeID":null},{"edgeID":"1594018","fromID":"1209997","toID":"1209996","formEdgeID":null},{"edgeID":"1594019","fromID":"1209991","toID":"1209998","formEdgeID":null},{"edgeID":"1594020","fromID":"1209998","toID":"1209995","formEdgeID":null},{"edgeID":"1594021","fromID":"1209998","toID":"1209999","formEdgeID":null},{"edgeID":"1594022","fromID":"1209999","toID":"1209990","formEdgeID":null},{"edgeID":"1594023","fromID":"1210002","toID":"1210001","formEdgeID":null},{"edgeID":"1594024","fromID":"1210003","toID":"1210002","formEdgeID":null},{"edgeID":"1594025","fromID":"1210001","toID":"1210004","formEdgeID":null},{"edgeID":"1594026","fromID":"1210004","toID":"1210000","formEdgeID":null},{"edgeID":"1594027","fromID":"1209995","toID":"1210005","formEdgeID":null},{"edgeID":"1594028","fromID":"1210005","toID":"1210001","formEdgeID":null},{"edgeID":"1594029","fromID":"1210008","toID":"1210007","formEdgeID":null},{"edgeID":"1594030","fromID":"1210009","toID":"1210008","formEdgeID":null},{"edgeID":"1594031","fromID":"1210007","toID":"1210010","formEdgeID":null},{"edgeID":"1594032","fromID":"1210010","toID":"1210006","formEdgeID":null},{"edgeID":"1594033","fromID":"1210013","toID":"1210012","formEdgeID":null},{"edgeID":"1594034","fromID":"1210014","toID":"1210013","formEdgeID":null},{"edgeID":"1594035","fromID":"1210012","toID":"1210015","formEdgeID":null},{"edgeID":"1594036","fromID":"1210015","toID":"1210011","formEdgeID":null},{"edgeID":"1594037","fromID":"1210011","toID":"1210016","formEdgeID":null},{"edgeID":"1594038","fromID":"1210016","toID":"1210006","formEdgeID":null},{"edgeID":"1594039","fromID":"1210006","toID":"1210017","formEdgeID":null},{"edgeID":"1594040","fromID":"1210017","toID":"1210000","formEdgeID":null},{"edgeID":"1594041","fromID":"1210001","toID":"1210018","formEdgeID":null},{"edgeID":"1594042","fromID":"1210018","toID":"1210007","formEdgeID":null},{"edgeID":"1594043","fromID":"1210018","toID":"1210019","formEdgeID":null},{"edgeID":"1594044","fromID":"1210019","toID":"1210017","formEdgeID":null},{"edgeID":"1594045","fromID":"1210007","toID":"1210020","formEdgeID":null},{"edgeID":"1594046","fromID":"1210020","toID":"1210012","formEdgeID":null},{"edgeID":"1594047","fromID":"1210020","toID":"1210021","formEdgeID":null},{"edgeID":"1594048","fromID":"1210021","toID":"1210016","formEdgeID":null},{"edgeID":"1594049","fromID":"1210024","toID":"1210023","formEdgeID":null},{"edgeID":"1594050","fromID":"1210025","toID":"1210024","formEdgeID":null},{"edgeID":"1594051","fromID":"1210023","toID":"1210026","formEdgeID":null},{"edgeID":"1594052","fromID":"1210026","toID":"1210022","formEdgeID":null},{"edgeID":"1594053","fromID":"1210006","toID":"1210027","formEdgeID":null},{"edgeID":"1594054","fromID":"1210027","toID":"1210022","formEdgeID":null},{"edgeID":"1594055","fromID":"1210007","toID":"1210028","formEdgeID":null},{"edgeID":"1594056","fromID":"1210028","toID":"1210023","formEdgeID":null},{"edgeID":"1594057","fromID":"1210028","toID":"1210029","formEdgeID":null},{"edgeID":"1594058","fromID":"1210029","toID":"1210027","formEdgeID":null},{"edgeID":"1594059","fromID":"1210032","toID":"1210031","formEdgeID":null},{"edgeID":"1594060","fromID":"1210033","toID":"1210032","formEdgeID":null},{"edgeID":"1594061","fromID":"1210031","toID":"1210034","formEdgeID":null},{"edgeID":"1594062","fromID":"1210034","toID":"1210030","formEdgeID":null},{"edgeID":"1594063","fromID":"1210036","toID":"1210035","formEdgeID":null},{"edgeID":"1594064","fromID":"1210037","toID":"1210036","formEdgeID":null},{"edgeID":"1594065","fromID":"1210031","toID":"1210038","formEdgeID":null},{"edgeID":"1594066","fromID":"1210038","toID":"1210035","formEdgeID":null},{"edgeID":"1594067","fromID":"1210035","toID":"1210039","formEdgeID":null},{"edgeID":"1594068","fromID":"1210039","toID":"1210030","formEdgeID":null},{"edgeID":"1594069","fromID":"1210042","toID":"1210041","formEdgeID":null},{"edgeID":"1594070","fromID":"1210043","toID":"1210042","formEdgeID":null},{"edgeID":"1594071","fromID":"1210041","toID":"1210044","formEdgeID":null},{"edgeID":"1594072","fromID":"1210044","toID":"1210040","formEdgeID":null},{"edgeID":"1594073","fromID":"1210047","toID":"1210046","formEdgeID":null},{"edgeID":"1594074","fromID":"1210048","toID":"1210047","formEdgeID":null},{"edgeID":"1594075","fromID":"1210046","toID":"1210049","formEdgeID":null},{"edgeID":"1594076","fromID":"1210049","toID":"1210045","formEdgeID":null},{"edgeID":"1594077","fromID":"1210045","toID":"1210050","formEdgeID":null},{"edgeID":"1594078","fromID":"1210050","toID":"1210040","formEdgeID":null},{"edgeID":"1594079","fromID":"1210041","toID":"1210051","formEdgeID":null},{"edgeID":"1594080","fromID":"1210051","toID":"1210046","formEdgeID":null},{"edgeID":"1594081","fromID":"1210051","toID":"1210052","formEdgeID":null},{"edgeID":"1594082","fromID":"1210052","toID":"1210050","formEdgeID":null},{"edgeID":"1594083","fromID":"1210054","toID":"1210053","formEdgeID":null},{"edgeID":"1594084","fromID":"1210055","toID":"1210054","formEdgeID":null},{"edgeID":"1594085","fromID":"1210046","toID":"1210056","formEdgeID":null},{"edgeID":"1594086","fromID":"1210056","toID":"1210053","formEdgeID":null},{"edgeID":"1594087","fromID":"1210056","toID":"1210057","formEdgeID":null},{"edgeID":"1594088","fromID":"1210057","toID":"1210045","formEdgeID":null}],"locutions":[{"nodeID":"1209991","personID":"3837","timestamp":"2023-08-24 19:03:47","start":"2023-05-16 17:45:47","end":null,"source":null},{"nodeID":"1209995","personID":"4054","timestamp":"2023-08-24 19:03:47","start":"2023-05-16 17:45:48","end":null,"source":null},{"nodeID":"1210001","personID":"3839","timestamp":"2023-08-24 19:03:47","start":"2023-05-16 17:45:52","end":null,"source":null},{"nodeID":"1210007","personID":"3837","timestamp":"2023-08-24 19:03:47","start":"2023-05-16 17:45:55","end":null,"source":null},{"nodeID":"1210012","personID":"3837","timestamp":"2023-08-24 19:03:47","start":"2023-05-16 17:45:56","end":null,"source":null},{"nodeID":"1210023","personID":"3837","timestamp":"2023-08-24 19:03:47","start":"2023-05-16 17:45:58","end":null,"source":null},{"nodeID":"1210031","personID":"3839","timestamp":"2023-08-24 19:03:47","start":"2023-05-16 17:46:27","end":null,"source":null},{"nodeID":"1210035","personID":"4054","timestamp":"2023-08-24 19:03:47","start":"2023-05-16 17:46:29","end":null,"source":null},{"nodeID":"1210041","personID":"3837","timestamp":"2023-08-24 19:03:47","start":"2023-05-16 17:46:36","end":null,"source":null},{"nodeID":"1210046","personID":"4054","timestamp":"2023-08-24 19:03:47","start":"2023-05-16 17:46:37","end":null,"source":null},{"nodeID":"1210053","personID":"3837","timestamp":"2023-08-24 19:03:47","start":"2023-05-16 17:46:38","end":null,"source":null}]}